remoteclick/__init__.py
remoteclick/datanode.py
remoteclick/datanode_value.py
remoteclick/value_type.py
remoteclick-0.1.2.dist-info/DESCRIPTION.rst
remoteclick-0.1.2.dist-info/METADATA
remoteclick-0.1.2.dist-info/RECORD
remoteclick-0.1.2.dist-info/WHEEL
remoteclick-0.1.2.dist-info/metadata.json
remoteclick-0.1.2.dist-info/top_level.txt
